yach/__init__.py
yach/stubs.py
yach-0.0.1a1.dist-info/LICENCE
yach-0.0.1a1.dist-info/METADATA
yach-0.0.1a1.dist-info/WHEEL
yach-0.0.1a1.dist-info/top_level.txt
yach-0.0.1a1.dist-info/RECORD
